pydbjson/__init__.py
pydbjson/pydbjson.py
pydbjson-0.0.4.dist-info/LICENSE
pydbjson-0.0.4.dist-info/METADATA
pydbjson-0.0.4.dist-info/WHEEL
pydbjson-0.0.4.dist-info/top_level.txt
pydbjson-0.0.4.dist-info/RECORD
