Metadata-Version: 2.1
Name: pydbjson
Version: 0.0.4
Summary: A small database using json
Author: Sampath
Author-email: gujarathisampath@gmail.com
Classifier: Development Status :: 1 - Planning
Classifier: Intended Audience :: Developers
Classifier: Programming Language :: Python :: 3
Classifier: Operating System :: Unix
Classifier: Operating System :: MacOS :: MacOS X
Classifier: Operating System :: Microsoft :: Windows
License-File: LICENSE
